testbench_cli_reporter/__init__.py
testbench_cli_reporter/__main__.py
testbench_cli_reporter/actions.py
testbench_cli_reporter/config_model.py
testbench_cli_reporter/execution.py
testbench_cli_reporter/log.py
testbench_cli_reporter/questions.py
testbench_cli_reporter/testbench.py
testbench_cli_reporter/util.py
testbench_cli_reporter-2.2.0.dist-info/entry_points.txt
testbench_cli_reporter-2.2.0.dist-info/licenses/LICENSE
testbench_cli_reporter-2.2.0.dist-info/WHEEL
testbench_cli_reporter-2.2.0.dist-info/METADATA
testbench_cli_reporter-2.2.0.dist-info/RECORD
