Metadata-Version: 2.4
Name: testbench-cli-reporter
Version: 2.2.0
Summary: CLI Tool to Export XML-Full-Reports from TestBench
Author-email: imbus AG | Zacharias Daum & René Rohner <rene.rohner@imbus.de>
Requires-Python: >=3.10
Classifier: Environment :: Console
Classifier: Programming Language :: Python :: 3
Classifier: Programming Language :: Python :: 3.10
Classifier: Operating System :: OS Independent
Classifier: License :: OSI Approved :: Apache Software License
Classifier: Topic :: Software Development :: Testing
Classifier: Topic :: Software Development :: Testing :: Acceptance
License-File: LICENSE
Requires-Dist: questionary>=2.1.0,<3.0.0
Requires-Dist: requests>=2.32.3,<3.0.0
Requires-Dist: urllib3>=2.4.0,<3.0.0
Requires-Dist: ruff>=0.11.8 ; extra == "dev"
Requires-Dist: pre-commit>=4.2.0 ; extra == "dev"
Requires-Dist: mypy>=1.15.0 ; extra == "dev"
Requires-Dist: flit>=3.12 ; extra == "dev"
Requires-Dist: wheel>=0.45.1 ; extra == "dev"
Requires-Dist: robotframework>=7.2.2 ; extra == "test"
Requires-Dist: robotframework-robocop>=6.1.1 ; extra == "test"
Project-URL: Homepage, https://github.com/imbus/testbench-cli-reporter
Provides-Extra: dev
Provides-Extra: test
